proxy_servant/__init__.py
proxy_servant/data_sources/__init__.py
proxy_servant/data_sources/file_data_source.py
proxy_servant/data_sources/i_data_source.py
proxy_servant/data_sources/list_data_source.py
proxy_servant/data_sources/union_data_source.py
proxy_servant/providers/__init__.py
proxy_servant/providers/basic_proxy_provider.py
proxy_servant/providers/i_proxy_provider.py
proxy_servant/proxy/__init__.py
proxy_servant/proxy/basic_proxy.py
proxy_servant/proxy/i_proxy.py
proxy_servant/proxy_checker/__init__.py
proxy_servant/proxy_checker/basic_proxy_checker.py
proxy_servant/proxy_checker/i_proxy_checker.py
proxy_servant-1.0.0.dist-info/LICENSE
proxy_servant-1.0.0.dist-info/METADATA
proxy_servant-1.0.0.dist-info/WHEEL
proxy_servant-1.0.0.dist-info/top_level.txt
proxy_servant-1.0.0.dist-info/RECORD
