Metadata-Version: 2.1
Name: proxy-servant
Version: 1.0.0
Summary: proxy-servant is your best friend that will give you a working proxy every time you request it
Home-page: https://github.com/FizzyShow/proxy_servant
Download-URL: https://pypi.org/project/proxy_servant/
Author: Dmitriy Popov
Author-email: dpopov@fizdm.ru
License: MIT
Keywords: Proxy,Proxy Checker,Proxy Servant,Servant,Python 3
License-File: LICENSE
Requires-Dist: aiohttp
Requires-Dist: aiosocksy
